# 极客时间Java训练营第一周作业
1.（选做）自己写一个简单的Hello.java，涉及基本类型，四则运算，if和for，然后自己分析一下对应的字节码，有问题群里讨论。

```java
public class Hello {
    public static void main(String[] args) {
        int a = 1;
        int b = 5;
        if (a < b) {
            System.out.println("a less than b");
        } else {
            System.out.println("a more than b");
        }
        System.out.println("a * b ="+(a*b));
        System.out.println("a / b ="+(a/b));
        System.out.println("a + b ="+(a+b));
        System.out.println("b - a ="+(b-a));
        int[] array = new int[]{10,5,20,6,8,2};
        int length = array.length;
        for (int i = 0; i < length; i++) {
            System.out.println(array[i]);
        }
    }
}
```

执行代码，打印结果：

>a less than b
>a * b =5
>a / b =0
>a + b =6
>b - a =4
>打印数组：
>10 5 20 6 8 2 

字节码分析：

> javac Hello.java

> javap -c Hello

```cmake
Compiled from "Hello.java"
public class org.nero.interview.geektime.Hello {
  public org.nero.interview.geektime.Hello();
    Code:
       0: aload_0   第0这个偏移位置加载到栈上来
       1: invokespecial #1                  // Method java/lang/Object."<init>":()V
       4: return

  public static void main(java.lang.String[]);
    Code:
       0: iconst_1  将值为1的常量压入栈中
       1: istore_1
       2: iconst_5  将值为5的常量压入栈中
       3: istore_2
       4: iload_1   在局部变量表中索引位置为1的地方装载变量
       5: iload_2   在局部变量表中索引位置为2的地方装载变量
       6: if_icmpge     20  判断a是否小于b，如果小于跳转到位置20
       9: getstatic     #2  获取2个字节的常量                // Field java/lang/System.out:Ljava/io/PrintStream;
      12: ldc           #3  加载常量                // String a less than b
      14: invokevirtual #4                  // Method java/io/PrintStream.println:(Ljava/lang/String;)V
      17: goto          28
      20: getstatic     #2                  // Field java/lang/System.out:Ljava/io/PrintStream;
      23: ldc           #5                  // String a more than b
      25: invokevirtual #4                  // Method java/io/PrintStream.println:(Ljava/lang/String;)V
      28: getstatic     #2                  // Field java/lang/System.out:Ljava/io/PrintStream;
      31: new           #6                  // class java/lang/StringBuilder
      34: dup
      35: invokespecial #7                  // Method java/lang/StringBuilder."<init>":()V
      38: ldc           #8                  // String a * b =
      40: invokevirtual #9                  // Method java/lang/StringBuilder.append:(Ljava/lang/String;)Ljava/lang/StringBuilder;
      43: iload_1
      44: iload_2
      45: imul
      46: invokevirtual #10                 // Method java/lang/StringBuilder.append:(I)Ljava/lang/StringBuilder;
      49: invokevirtual #11                 // Method java/lang/StringBuilder.toString:()Ljava/lang/String;
      52: invokevirtual #4                  // Method java/io/PrintStream.println:(Ljava/lang/String;)V
      55: getstatic     #2                  // Field java/lang/System.out:Ljava/io/PrintStream;
      58: new           #6                  // class java/lang/StringBuilder
      61: dup
      62: invokespecial #7                  // Method java/lang/StringBuilder."<init>":()V
      65: ldc           #12                 // String a / b =
      67: invokevirtual #9                  // Method java/lang/StringBuilder.append:(Ljava/lang/String;)Ljava/lang/StringBuilder;
      70: iload_1
      71: iload_2
      72: idiv
      73: invokevirtual #10                 // Method java/lang/StringBuilder.append:(I)Ljava/lang/StringBuilder;
      76: invokevirtual #11                 // Method java/lang/StringBuilder.toString:()Ljava/lang/String;
      79: invokevirtual #4                  // Method java/io/PrintStream.println:(Ljava/lang/String;)V
      82: getstatic     #2                  // Field java/lang/System.out:Ljava/io/PrintStream;
      85: new           #6                  // class java/lang/StringBuilder
      88: dup
      89: invokespecial #7                  // Method java/lang/StringBuilder."<init>":()V
      92: ldc           #13                 // String a + b =
      94: invokevirtual #9                  // Method java/lang/StringBuilder.append:(Ljava/lang/String;)Ljava/lang/StringBuilder;
      97: iload_1
      98: iload_2
      99: iadd
     100: invokevirtual #10                 // Method java/lang/StringBuilder.append:(I)Ljava/lang/StringBuilder;
     103: invokevirtual #11                 // Method java/lang/StringBuilder.toString:()Ljava/lang/String;
     106: invokevirtual #4                  // Method java/io/PrintStream.println:(Ljava/lang/String;)V
     109: getstatic     #2                  // Field java/lang/System.out:Ljava/io/PrintStream;
     112: new           #6                  // class java/lang/StringBuilder
     115: dup
     116: invokespecial #7                  // Method java/lang/StringBuilder."<init>":()V
     119: ldc           #14                 // String b - a =
     121: invokevirtual #9                  // Method java/lang/StringBuilder.append:(Ljava/lang/String;)Ljava/lang/StringBuilder;
     124: iload_2
     125: iload_1
     126: isub
     127: invokevirtual #10                 // Method java/lang/StringBuilder.append:(I)Ljava/lang/StringBuilder;
     130: invokevirtual #11                 // Method java/lang/StringBuilder.toString:()Ljava/lang/String;
     133: invokevirtual #4                  // Method java/io/PrintStream.println:(Ljava/lang/String;)V
     136: bipush        6     压入栈中6个字节值
     138: newarray       int
     140: dup
     141: iconst_0
     142: bipush        10
     144: iastore
     145: dup
     146: iconst_1
     147: iconst_5
     148: iastore
     149: dup
     150: iconst_2
     151: bipush        20
     153: iastore
     154: dup
     155: iconst_3
     156: bipush        6
     158: iastore
     159: dup
     160: iconst_4
     161: bipush        8
     163: iastore
     164: dup
     165: iconst_5
     166: iconst_2
     167: iastore
     168: astore_3
     169: aload_3
     170: arraylength
     171: istore        4
     173: getstatic     #2                  // Field java/lang/System.out:Ljava/io/PrintStream;
     176: ldc           #15                 // String 打印数组：
     178: invokevirtual #4                  // Method java/io/PrintStream.println:(Ljava/lang/String;)V
     181: iconst_0
     182: istore        5
     184: iload         5
     186: iload         4
     188: if_icmpge     215
     191: getstatic     #2                  // Field java/lang/System.out:Ljava/io/PrintStream;
     194: aload_3
     195: iload         5
     197: iaload
     198: invokevirtual #16                 // Method java/io/PrintStream.print:(I)V
     201: getstatic     #2                  // Field java/lang/System.out:Ljava/io/PrintStream;
     204: ldc           #17                 // String
     206: invokevirtual #18                 // Method java/io/PrintStream.print:(Ljava/lang/String;)V
     209: iinc          5, 1
     212: goto          184
     215: return
}
```



2.（必做）自定义一个Classloader，加载一个Hello.xlass文件，执行hello方法，此文件内容是一个Hello.class文件所有字节（x=255-x）处理后的文件。文件群里提供。

```java
import java.io.*;
import java.lang.reflect.Method;

public class HelloClassLoader extends ClassLoader {
    public static void main(String[] args) throws Exception {
        Object instance = new HelloClassLoader().findClass("Hello").newInstance();
        Method method = instance.getClass().getMethod("hello");
        System.out.println("执行Hello.xlass文件的hello方法：");
        System.out.println(method.invoke(instance));
    }

    @Override
    protected Class<?> findClass(String name) throws ClassNotFoundException {
        try {
            File file = new File("Hello/Hello.xlass");
            InputStream fileIn = new FileInputStream(file);
            BufferedInputStream in = new BufferedInputStream(fileIn);
            byte[] bytes = in.readAllBytes();
          	int length = bytes.length;
            for (int i = 0; i < length; i++) {
                bytes[i] = (byte) (0xff - bytes[i]);
            }
            return defineClass(name, bytes, 0, length);
        } catch (FileNotFoundException e) {
            return defineClass(name, new byte[]{}, 0, 0);
        } catch (IOException e) {
            return defineClass(name, new byte[]{}, 0, 0);
        }
    }

}
```

执行代码，打印结果：

>执行Hello.xlass文件的hello方法：
>Hello, classLoader!
>null

3.（必做）画一张图，展示Xmx、Xms、Xmn、Meta、DirectMemory、Xss这些内存参数的关系。

**请见文件：jvm配置关系图.png**

4.（选做）检查一下自己维护的业务系统的JVM参数配置，用jstat和jstack、jmap查看一下详情，并且自己独立分析一下大概情况，思考有没有不合理的地方，如何改进。

注意：如果没有线上系统，可以自己run一个web/java项目。

第一步：jstack查看进程使用情况jstack 2743

这里截取了一部分结果，可以看到pushMsg-schedule-pool-1到pushMsg-schedule-pool-5这5个线程等待nioEventLoopGroup-3-1释放锁住的那块内存。

怀疑时NioEventLoop运行太多，导致连接数太多响应不了。

>"pushMsg-schedule-pool-5" #40 daemon prio=5 os_prio=0 tid=0x00007f6450002800 nid=0xb6c waiting on condition [0x00007f6443ffe000]
>
>java.lang.Thread.State: TIMED_WAITING (parking)
>
>at sun.misc.Unsafe.park(Native Method)
>
>\- parking to wait for <0x00000000e0bf6338> (a java.util.concurrent.locks.AbstractQueuedSynchronizer$ConditionObject)
>
>at java.util.concurrent.locks.LockSupport.parkNanos(LockSupport.java:215)
>
>at java.util.concurrent.locks.AbstractQueuedSynchronizer$ConditionObject.awaitNanos(AbstractQueuedSynchronizer.java:2078)
>
>at java.util.concurrent.ScheduledThreadPoolExecutor$DelayedWorkQueue.take(ScheduledThreadPoolExecutor.java:1093)
>
>at java.util.concurrent.ScheduledThreadPoolExecutor$DelayedWorkQueue.take(ScheduledThreadPoolExecutor.java:809)
>
>at java.util.concurrent.ThreadPoolExecutor.getTask(ThreadPoolExecutor.java:1074)
>
>at java.util.concurrent.ThreadPoolExecutor.runWorker(ThreadPoolExecutor.java:1134)
>
>at java.util.concurrent.ThreadPoolExecutor$Worker.run(ThreadPoolExecutor.java:624)
>
>at java.lang.Thread.run(Thread.java:748)
>
>"pushMsg-schedule-pool-4" #39 daemon prio=5 os_prio=0 tid=0x00007f6450001000 nid=0xb63 waiting on condition [0x00007f64b01ce000]
>
>java.lang.Thread.State: WAITING (parking)
>
>at sun.misc.Unsafe.park(Native Method)
>
>\- parking to wait for <0x00000000e0bf6338> (a java.util.concurrent.locks.AbstractQueuedSynchronizer$ConditionObject)
>
>at java.util.concurrent.locks.LockSupport.park(LockSupport.java:175)
>
>at java.util.concurrent.locks.AbstractQueuedSynchronizer$ConditionObject.await(AbstractQueuedSynchronizer.java:2039)
>
>at java.util.concurrent.ScheduledThreadPoolExecutor$DelayedWorkQueue.take(ScheduledThreadPoolExecutor.java:1088)
>
>at java.util.concurrent.ScheduledThreadPoolExecutor$DelayedWorkQueue.take(ScheduledThreadPoolExecutor.java:809)
>
>at java.util.concurrent.ThreadPoolExecutor.getTask(ThreadPoolExecutor.java:1074)
>
>at java.util.concurrent.ThreadPoolExecutor.runWorker(ThreadPoolExecutor.java:1134)
>
>at java.util.concurrent.ThreadPoolExecutor$Worker.run(ThreadPoolExecutor.java:624)
>
>at java.lang.Thread.run(Thread.java:748)
>
>"pushMsg-schedule-pool-3" #38 daemon prio=5 os_prio=0 tid=0x00007f644c004800 nid=0xb5b waiting on condition [0x00007f64b02cf000]
>
>java.lang.Thread.State: WAITING (parking)
>
>at sun.misc.Unsafe.park(Native Method)
>
>\- parking to wait for <0x00000000e0bf6338> (a java.util.concurrent.locks.AbstractQueuedSynchronizer$ConditionObject)
>
>at java.util.concurrent.locks.LockSupport.park(LockSupport.java:175)
>
>at java.util.concurrent.locks.AbstractQueuedSynchronizer$ConditionObject.await(AbstractQueuedSynchronizer.java:2039)
>
>at java.util.concurrent.ScheduledThreadPoolExecutor$DelayedWorkQueue.take(ScheduledThreadPoolExecutor.java:1088)
>
>at java.util.concurrent.ScheduledThreadPoolExecutor$DelayedWorkQueue.take(ScheduledThreadPoolExecutor.java:809)
>
>at java.util.concurrent.ThreadPoolExecutor.getTask(ThreadPoolExecutor.java:1074)
>
>at java.util.concurrent.ThreadPoolExecutor.runWorker(ThreadPoolExecutor.java:1134)
>
>at java.util.concurrent.ThreadPoolExecutor$Worker.run(ThreadPoolExecutor.java:624)
>
>at java.lang.Thread.run(Thread.java:748)
>
>"pushMsg-schedule-pool-2" #37 daemon prio=5 os_prio=0 tid=0x00007f644c003000 nid=0xb55 waiting on condition [0x00007f64b03d0000]
>
>java.lang.Thread.State: WAITING (parking)
>
>at sun.misc.Unsafe.park(Native Method)
>
>\- parking to wait for <0x00000000e0bf6338> (a java.util.concurrent.locks.AbstractQueuedSynchronizer$ConditionObject)
>
>at java.util.concurrent.locks.LockSupport.park(LockSupport.java:175)
>
>at java.util.concurrent.locks.AbstractQueuedSynchronizer$ConditionObject.await(AbstractQueuedSynchronizer.java:2039)
>
>at java.util.concurrent.ScheduledThreadPoolExecutor$DelayedWorkQueue.take(ScheduledThreadPoolExecutor.java:1088)
>
>at java.util.concurrent.ScheduledThreadPoolExecutor$DelayedWorkQueue.take(ScheduledThreadPoolExecutor.java:809)
>
>at java.util.concurrent.ThreadPoolExecutor.getTask(ThreadPoolExecutor.java:1074)
>
>at java.util.concurrent.ThreadPoolExecutor.runWorker(ThreadPoolExecutor.java:1134)
>
>at java.util.concurrent.ThreadPoolExecutor$Worker.run(ThreadPoolExecutor.java:624)
>
>at java.lang.Thread.run(Thread.java:748)
>
>"pushMsg-schedule-pool-1" #36 daemon prio=5 os_prio=0 tid=0x00007f6458221000 nid=0xb54 waiting on condition [0x00007f64b04d1000]
>
>java.lang.Thread.State: WAITING (parking)
>
>at sun.misc.Unsafe.park(Native Method)
>
>\- parking to wait for <0x00000000e0bf6338> (a java.util.concurrent.locks.AbstractQueuedSynchronizer$ConditionObject)
>
>at java.util.concurrent.locks.LockSupport.park(LockSupport.java:175)
>
>at java.util.concurrent.locks.AbstractQueuedSynchronizer$ConditionObject.await(AbstractQueuedSynchronizer.java:2039)
>
>at java.util.concurrent.ScheduledThreadPoolExecutor$DelayedWorkQueue.take(ScheduledThreadPoolExecutor.java:1088)
>
>at java.util.concurrent.ScheduledThreadPoolExecutor$DelayedWorkQueue.take(ScheduledThreadPoolExecutor.java:809)
>
>at java.util.concurrent.ThreadPoolExecutor.getTask(ThreadPoolExecutor.java:1074)
>
>at java.util.concurrent.ThreadPoolExecutor.runWorker(ThreadPoolExecutor.java:1134)
>
>at java.util.concurrent.ThreadPoolExecutor$Worker.run(ThreadPoolExecutor.java:624)
>
>at java.lang.Thread.run(Thread.java:748)
>
>"nioEventLoopGroup-3-1" #35 prio=10 os_prio=0 tid=0x00007f6454059800 nid=0xb53 runnable [0x00007f64b15d3000]
>
>java.lang.Thread.State: RUNNABLE
>
>at sun.nio.ch.EPollArrayWrapper.epollWait(Native Method)
>
>at sun.nio.ch.EPollArrayWrapper.poll(EPollArrayWrapper.java:269)
>
>at sun.nio.ch.EPollSelectorImpl.doSelect(EPollSelectorImpl.java:93)
>
>at sun.nio.ch.SelectorImpl.lockAndDoSelect(SelectorImpl.java:86)
>
>\- locked <0x00000000e0c01000> (a io.netty.channel.nio.SelectedSelectionKeySet)
>
>\- locked <0x00000000e0c00ff0> (a java.util.Collections$UnmodifiableSet)
>
>\- locked <0x00000000e0c00fa8> (a sun.nio.ch.EPollSelectorImpl)
>
>at sun.nio.ch.SelectorImpl.select(SelectorImpl.java:97)
>
>at io.netty.channel.nio.SelectedSelectionKeySetSelector.select(SelectedSelectionKeySetSelector.java:62)
>
>at io.netty.channel.nio.NioEventLoop.select(NioEventLoop.java:756)
>
>at io.netty.channel.nio.NioEventLoop.run(NioEventLoop.java:411)
>
>at io.netty.util.concurrent.SingleThreadEventExecutor$5.run(SingleThreadEventExecutor.java:884)
>
>at io.netty.util.concurrent.FastThreadLocalRunnable.run(FastThreadLocalRunnable.java:30)
>
>at java.lang.Thread.run(Thread.java:748)
>
>"DestroyJavaVM" #34 prio=5 os_prio=0 tid=0x00007f6510009000 nid=0xab8 waiting on condition [0x0000000000000000]
>
>java.lang.Thread.State: RUNNABLE
>
>"nioEventLoopGroup-2-1" #31 prio=10 os_prio=0 tid=0x00007f65116a5000 nid=0xb03 runnable [0x00007f64b18d4000]
>
>java.lang.Thread.State: RUNNABLE
>
>at sun.nio.ch.EPollArrayWrapper.epollWait(Native Method)
>
>at sun.nio.ch.EPollArrayWrapper.poll(EPollArrayWrapper.java:269)
>
>at sun.nio.ch.EPollSelectorImpl.doSelect(EPollSelectorImpl.java:93)
>
>at sun.nio.ch.SelectorImpl.lockAndDoSelect(SelectorImpl.java:86)
>
>\- locked <0x00000000e0b2de48> (a io.netty.channel.nio.SelectedSelectionKeySet)
>
>\- locked <0x00000000e0b2ef20> (a java.util.Collections$UnmodifiableSet)
>
>\- locked <0x00000000e0b2dda0> (a sun.nio.ch.EPollSelectorImpl)
>
>at sun.nio.ch.SelectorImpl.select(SelectorImpl.java:97)
>
>at io.netty.channel.nio.SelectedSelectionKeySetSelector.select(SelectedSelectionKeySetSelector.java:62)
>
>at io.netty.channel.nio.NioEventLoop.select(NioEventLoop.java:756)
>
>at io.netty.channel.nio.NioEventLoop.run(NioEventLoop.java:411)
>
>at io.netty.util.concurrent.SingleThreadEventExecutor$5.run(SingleThreadEventExecutor.java:884)
>
>at io.netty.util.concurrent.FastThreadLocalRunnable.run(FastThreadLocalRunnable.java:30)
>
>at java.lang.Thread.run(Thread.java:748)
>
>"ObjectCleanerThread" #30 daemon prio=1 os_prio=0 tid=0x00007f651169d000 nid=0xb02 in Object.wait() [0x00007f64c4202000]
>
>java.lang.Thread.State: TIMED_WAITING (on object monitor)
>
>at java.lang.Object.wait(Native Method)
>
>at java.lang.ref.ReferenceQueue.remove(ReferenceQueue.java:143)
>
>\- locked <0x00000000e0ab9230> (a java.lang.ref.ReferenceQueue$Lock)
>
>at io.netty.util.internal.ObjectCleaner$1.run(ObjectCleaner.java:54)
>
>at io.netty.util.concurrent.FastThreadLocalRunnable.run(FastThreadLocalRunnable.java:30)
>
>at java.lang.Thread.run(Thread.java:748)
>
>"commons-pool-EvictionTimer" #29 daemon prio=5 os_prio=0 tid=0x00007f6510bef800 nid=0xb00 in Object.wait() [0x00007f64c4101000]
>
>java.lang.Thread.State: TIMED_WAITING (on object monitor)
>
>at java.lang.Object.wait(Native Method)
>
>at java.util.TimerThread.mainLoop(Timer.java:552)
>
>\- locked <0x00000000e0b94108> (a java.util.TaskQueue)
>
>at java.util.TimerThread.run(Timer.java:505)
>
>"pool-3-thread-1" #27 prio=5 os_prio=0 tid=0x00007f6510f66800 nid=0xafe waiting on condition [0x00007f64c4303000]
>
>java.lang.Thread.State: TIMED_WAITING (parking)
>
>at sun.misc.Unsafe.park(Native Method)
>
>\- parking to wait for <0x00000000e0764f38> (a java.util.concurrent.locks.AbstractQueuedSynchronizer$ConditionObject)
>
>at java.util.concurrent.locks.LockSupport.parkNanos(LockSupport.java:215)
>
>at java.util.concurrent.locks.AbstractQueuedSynchronizer$ConditionObject.awaitNanos(AbstractQueuedSynchronizer.java:2078)
>
>at java.util.concurrent.ScheduledThreadPoolExecutor$DelayedWorkQueue.take(ScheduledThreadPoolExecutor.java:1093)
>
>at java.util.concurrent.ScheduledThreadPoolExecutor$DelayedWorkQueue.take(ScheduledThreadPoolExecutor.java:809)
>
>at java.util.concurrent.ThreadPoolExecutor.getTask(ThreadPoolExecutor.java:1074)
>
>at java.util.concurrent.ThreadPoolExecutor.runWorker(ThreadPoolExecutor.java:1134)
>
>at java.util.concurrent.ThreadPoolExecutor$Worker.run(ThreadPoolExecutor.java:624)
>
>at java.lang.Thread.run(Thread.java:748)
>
>"main-EventThread" #25 daemon prio=5 os_prio=0 tid=0x00007f6510a73800 nid=0xaf8 waiting on condition [0x00007f64c481b000]
>
>java.lang.Thread.State: WAITING (parking)
>
>at sun.misc.Unsafe.park(Native Method)
>
>\- parking to wait for <0x00000000e07cadf0> (a java.util.concurrent.locks.AbstractQueuedSynchronizer$ConditionObject)
>
>at java.util.concurrent.locks.LockSupport.park(LockSupport.java:175)
>
>at java.util.concurrent.locks.AbstractQueuedSynchronizer$ConditionObject.await(AbstractQueuedSynchronizer.java:2039)
>
>at java.util.concurrent.LinkedBlockingQueue.take(LinkedBlockingQueue.java:442)
>
>at org.apache.zookeeper.ClientCnxn$EventThread.run(ClientCnxn.java:501)
>
>"main-SendThread(10.59.8.31:2181)" #24 daemon prio=5 os_prio=0 tid=0x00007f6510a70000 nid=0xaf7 runnable [0x00007f64c551d000]
>
>java.lang.Thread.State: RUNNABLE
>
>at sun.nio.ch.EPollArrayWrapper.epollWait(Native Method)
>
>at sun.nio.ch.EPollArrayWrapper.poll(EPollArrayWrapper.java:269)
>
>at sun.nio.ch.EPollSelectorImpl.doSelect(EPollSelectorImpl.java:93)
>
>at sun.nio.ch.SelectorImpl.lockAndDoSelect(SelectorImpl.java:86)
>
>\- locked <0x00000000e08176d8> (a sun.nio.ch.Util$3)
>
>\- locked <0x00000000e08176c8> (a java.util.Collections$UnmodifiableSet)
>
>\- locked <0x00000000e0817260> (a sun.nio.ch.EPollSelectorImpl)
>
>at sun.nio.ch.SelectorImpl.select(SelectorImpl.java:97)
>
>at org.apache.zookeeper.ClientCnxnSocketNIO.doTransport(ClientCnxnSocketNIO.java:349)
>
>at org.apache.zookeeper.ClientCnxn$SendThread.run(ClientCnxn.java:1141)
>
>"Service Thread" #17 daemon prio=9 os_prio=0 tid=0x00007f65102d6000 nid=0xadb runnable [0x0000000000000000]
>
>java.lang.Thread.State: RUNNABLE
>
>"C1 CompilerThread11" #16 daemon prio=9 os_prio=0 tid=0x00007f65102d3000 nid=0xad8 waiting on condition [0x0000000000000000]
>
>java.lang.Thread.State: RUNNABLE
>
>"C1 CompilerThread10" #15 daemon prio=9 os_prio=0 tid=0x00007f65102d0800 nid=0xad7 waiting on condition [0x0000000000000000]
>
>java.lang.Thread.State: RUNNABLE
>
>"C1 CompilerThread9" #14 daemon prio=9 os_prio=0 tid=0x00007f65102ce800 nid=0xad6 waiting on condition [0x0000000000000000]
>
>java.lang.Thread.State: RUNNABLE
>
>"C1 CompilerThread8" #13 daemon prio=9 os_prio=0 tid=0x00007f65102cc800 nid=0xad4 waiting on condition [0x0000000000000000]
>
>java.lang.Thread.State: RUNNABLE
>
>"C2 CompilerThread7" #12 daemon prio=9 os_prio=0 tid=0x00007f65102ca000 nid=0xad3 waiting on condition [0x0000000000000000]
>
>java.lang.Thread.State: RUNNABLE
>
>"C2 CompilerThread6" #11 daemon prio=9 os_prio=0 tid=0x00007f65102c8000 nid=0xad2 waiting on condition [0x0000000000000000]
>
>java.lang.Thread.State: RUNNABLE
>
>"C2 CompilerThread5" #10 daemon prio=9 os_prio=0 tid=0x00007f65102c6000 nid=0xad1 waiting on condition [0x0000000000000000]
>
>java.lang.Thread.State: RUNNABLE
>
>"C2 CompilerThread4" #9 daemon prio=9 os_prio=0 tid=0x00007f65102bb800 nid=0xacf waiting on condition [0x0000000000000000]
>
>java.lang.Thread.State: RUNNABLE
>
>"C2 CompilerThread3" #8 daemon prio=9 os_prio=0 tid=0x00007f65102b9800 nid=0xace runnable [0x0000000000000000]
>
>java.lang.Thread.State: RUNNABLE
>
>"C2 CompilerThread2" #7 daemon prio=9 os_prio=0 tid=0x00007f65102b7800 nid=0xacd waiting on condition [0x0000000000000000]
>
>java.lang.Thread.State: RUNNABLE
>
>"C2 CompilerThread1" #6 daemon prio=9 os_prio=0 tid=0x00007f65102b5800 nid=0xacc waiting on condition [0x0000000000000000]
>
>java.lang.Thread.State: RUNNABLE
>
>"C2 CompilerThread0" #5 daemon prio=9 os_prio=0 tid=0x00007f65102b2800 nid=0xacb waiting on condition [0x0000000000000000]
>
>java.lang.Thread.State: RUNNABLE
>
>"Signal Dispatcher" #4 daemon prio=9 os_prio=0 tid=0x00007f65102b1000 nid=0xaca runnable [0x0000000000000000]
>
>java.lang.Thread.State: RUNNABLE
>
>"Finalizer" #3 daemon prio=8 os_prio=0 tid=0x00007f651027e000 nid=0xac8 in Object.wait() [0x00007f64c73f2000]
>
>java.lang.Thread.State: WAITING (on object monitor)
>
>at java.lang.Object.wait(Native Method)
>
>at java.lang.ref.ReferenceQueue.remove(ReferenceQueue.java:143)
>
>\- locked <0x00000000e00e67e8> (a java.lang.ref.ReferenceQueue$Lock)
>
>at java.lang.ref.ReferenceQueue.remove(ReferenceQueue.java:164)
>
>at java.lang.ref.Finalizer$FinalizerThread.run(Finalizer.java:209)
>
>"Reference Handler" #2 daemon prio=10 os_prio=0 tid=0x00007f6510279000 nid=0xac7 in Object.wait() [0x00007f64c74f3000]
>
>java.lang.Thread.State: WAITING (on object monitor)
>
>at java.lang.Object.wait(Native Method)
>
>at java.lang.Object.wait(Object.java:502)
>
>at java.lang.ref.Reference.tryHandlePending(Reference.java:191)
>
>\- locked <0x00000000e00e6a60> (a java.lang.ref.Reference$Lock)
>
>at java.lang.ref.Reference$ReferenceHandler.run(Reference.java:153)
>
>"VM Thread" os_prio=0 tid=0x00007f6510271800 nid=0xac6 runnable
>
>"GC task thread#0 (ParallelGC)" os_prio=0 tid=0x00007f651001e800 nid=0xab9 runnable
>
>"GC task thread#1 (ParallelGC)" os_prio=0 tid=0x00007f6510020800 nid=0xaba runnable
>
>"GC task thread#2 (ParallelGC)" os_prio=0 tid=0x00007f6510022000 nid=0xabb runnable
>
>"GC task thread#3 (ParallelGC)" os_prio=0 tid=0x00007f6510024000 nid=0xabc runnable
>
>"GC task thread#4 (ParallelGC)" os_prio=0 tid=0x00007f6510025800 nid=0xabd runnable
>
>"GC task thread#5 (ParallelGC)" os_prio=0 tid=0x00007f6510027800 nid=0xabe runnable
>
>"GC task thread#6 (ParallelGC)" os_prio=0 tid=0x00007f6510029800 nid=0xabf runnable
>
>"GC task thread#7 (ParallelGC)" os_prio=0 tid=0x00007f651002b000 nid=0xac0 runnable
>
>"GC task thread#8 (ParallelGC)" os_prio=0 tid=0x00007f651002d000 nid=0xac1 runnable
>
>"GC task thread#9 (ParallelGC)" os_prio=0 tid=0x00007f651002f000 nid=0xac2 runnable
>
>"GC task thread#10 (ParallelGC)" os_prio=0 tid=0x00007f6510030800 nid=0xac3 runnable
>
>"GC task thread#11 (ParallelGC)" os_prio=0 tid=0x00007f6510032800 nid=0xac4 runnable
>
>"GC task thread#12 (ParallelGC)" os_prio=0 tid=0x00007f6510034800 nid=0xac5 runnable
>
>"VM Periodic Task Thread" os_prio=0 tid=0x00007f65102da800 nid=0xadc waiting on condition
>
>JNI global references: 702

第二步：JMap查内存

>num #instances #bytes class name
>
>\----------------------------------------------
>
>1: 64375 238175704 [B
>
>2: 142437 158343616 [C
>
>3: 58181 8101248 [Ljava.lang.Object;
>
>4: 188674 6037568 java.lang.ThreadLocal$ThreadLocalMap$Entry
>
>5: 13954 5246704 java.lang.Thread
>
>6: 31931 2795680 [I
>
>7: 13891 2007408 [Ljava.lang.ThreadLocal$ThreadLocalMap$Entry;
>
>8: 29294 1640464 sun.nio.cs.UTF_8$Encoder
>
>9: 2496 1637376 io.netty.util.internal.shaded.org.jctools.queues.MpscArrayQueue
>
>10: 13888 1444352 org.apache.logging.log4j.core.impl.MutableLogEvent
>
>11: 28177 1352496 java.nio.HeapCharBuffer
>
>12: 28150 1351200 java.nio.HeapByteBuffer
>
>13: 54527 1308648 java.lang.String
>
>14: 2145 1302480 [Lio.netty.util.Recycler$DefaultHandle;
>
>15: 29408 1176320 java.lang.ref.SoftReference
>
>16: 32529 1040928 java.util.HashMap$Node
>
>17: 14259 1026648 org.apache.logging.log4j.core.util.datetime.FixedDateFormat
>
>18: 14266 798896 sun.util.calendar.ZoneInfo
>
>19: 7005 785216 java.lang.Class
>
>20: 48180 770880 java.lang.Object
>
>21: 31106 746544 java.lang.StringBuilder
>
>22: 16734 669360 io.netty.util.DefaultAttributeMap$DefaultAttribute
>
>23: 13936 668928 java.util.concurrent.ThreadPoolExecutor$Worker
>
>24: 7512 634376 [Ljava.util.HashMap$Node;
>
>25: 19796 633472 java.util.concurrent.ConcurrentHashMap$Node
>
>26: 14259 570360 org.apache.logging.log4j.core.pattern.DatePatternConverter$FixedFormatter
>
>27: 17324 554368 java.lang.StackTraceElement
>
>28: 16733 535456 java.util.concurrent.locks.AbstractQueuedSynchronizer$Node
>
>29: 14687 352488 org.apache.logging.log4j.core.time.MutableInstant
>
>30: 2855 352480 [Ljava.nio.channels.SelectionKey;
>
>31: 13891 333384 java.lang.ThreadLocal$ThreadLocalMap
>
>32: 6708 321984 java.util.HashMap
>
>33: 2790 312480 sun.nio.ch.SocketChannelImpl
>
>34: 2789 290056 io.netty.channel.socket.nio.NioSocketChannel
>
>35: 2789 223120 [Ljava.util.concurrent.RunnableScheduledFuture;
>
>36: 2789 223120 java.util.concurrent.ScheduledThreadPoolExecutor
>
>37: 13888 222208 org.apache.logging.log4j.message.ReusableSimpleMessage
>
>38: 2790 200880 io.netty.channel.AdaptiveRecvByteBufAllocator$HandleImpl
>
>39: 2790 200880 io.netty.channel.DefaultChannelPipeline$HeadContext
>
>40: 2790 200880 io.netty.channel.DefaultChannelPipeline$TailContext
>
>41: 2788 200736 java.util.concurrent.ScheduledThreadPoolExecutor$ScheduledFutureTask
>
>42: 6180 197760 java.util.concurrent.locks.ReentrantLock$NonfairSync
>
>43: 5681 181792 java.net.InetAddress$InetAddressHolder
>
>44: 2834 180752 [Ljava.security.ProtectionDomain;

其中，占用空间最大的前几个class name是：

> [B  代表byte[]
>
> [C  代表char[]
>
> [Ljava.lang.Object  代表object[]
>
> java.lang.ThreadLocal$ThreadLocalMap$Entry  代表ThreadLocal类下的ThreadLocalMap类下的Entry对象
>
> java.lang.Thread  代表线程对象
>
> [I  代表int[]

五、jmap -heap 2743 查看内存堆信息

>Attaching to process ID 2743, please wait...
>
>Debugger attached successfully.
>
>Server compiler detected.
>
>JVM version is 25.152-b16
>
>using thread-local object allocation.
>
>Parallel GC with 13 thread(s)
>
>Heap Configuration:
>
>MinHeapFreeRatio = 0
>
>MaxHeapFreeRatio = 100
>
>MaxHeapSize = 536870912 (512.0MB)
>
>NewSize = 175112192 (167.0MB)
>
>MaxNewSize = 178782208 (170.5MB)
>
>OldSize = 351272960 (335.0MB)
>
>NewRatio = 2
>
>SurvivorRatio = 8
>
>MetaspaceSize = 21807104 (20.796875MB)
>
>CompressedClassSpaceSize = 1073741824 (1024.0MB)
>
>MaxMetaspaceSize = 17592186044415 MB
>
>G1HeapRegionSize = 0 (0.0MB)
>
>Heap Usage:
>
>PS Young Generation
>
>Eden Space:
>
>capacity = 173539328 (165.5MB)
>
>used = 173539328 (165.5MB)
>
>free = 0 (0.0MB)
>
>100.0% used
>
>From Space:
>
>capacity = 2621440 (2.5MB)
>
>used = 0 (0.0MB)
>
>free = 2621440 (2.5MB)
>
>0.0% used
>
>To Space:
>
>capacity = 2621440 (2.5MB)
>
>used = 0 (0.0MB)
>
>free = 2621440 (2.5MB)
>
>0.0% used
>
>PS Old Generation
>
>capacity = 358088704 (341.5MB)
>
>used = 357875160 (341.29634857177734MB)
>
>free = 213544 (0.20365142822265625MB)
>
>99.94036561399044% used
>
>10989 interned Strings occupying 1061928 bytes.

可以看到老年代和年轻代Eden区的内存被占用满了。

第三步：通过工具**Memory Analyzer**分析堆

jmap -dump:live,format=b,file=heap2743.bin 2743 将堆dump到文件heap2743.bin文件中，通过工具打开该文件看到如下：

**请见文件：Memory Analyzer分析饼图.png**

通过点击details，然后在中间页，点击弹出的菜单栏中的”list_objects"项，找到如下的：

**请见文件：Memory Analyzer分析详细执行步骤.png**

经排查，发现这是老代码，之前在每次连接后，运行一个5核心数的线程池，而且也不随客户端断开连接后释放，导致每次连接都要有5个线程，所以导致线程不够申请的了。

**最终解决方案**：

1.将线程池改成单线程

```java
@OnOpen
public void onOpen(final Session session, HttpHeaders headers, ParameterMap parameterMap) throws IOException {
	String cityCode = parameterMap.getParameter("cityCode");
	final String driverCode = parameterMap.getParameter("driverCode");
	long connTime = System.currentTimeMillis();
	ScheduledExecutorService sc = Executors.newSingleThreadScheduledExecutor();
}
```

这里之前是5个核心数的线程池，当初其实是希望将整体websocket连接中的长连接的推送逻辑保持在5个常驻线程的量，如果超出后要等待，其实后面想了一下即便这里改成这个，也会造成问题，因为推送逻辑是始终保持的，那么如果实现成这样了，就只能支持5个司机的推送，再多就不支持了。

2.客户端断开连接时未释放长连接推送逻辑的线程

```java
@OnOpen
public void onOpen(final Session session, HttpHeaders headers, ParameterMap parameterMap) throws IOException {
  String cityCode = parameterMap.getParameter("cityCode");
  final String driverCode = parameterMap.getParameter("driverCode");
  long connTime = System.currentTimeMillis();
  ScheduledExecutorService sc = Executors.newSingleThreadScheduledExecutor();
  
  selfM.put("cityCode", cityCode);
  selfM.put("driverCode", driverCode);
  selfM.put("connTime", connTime);
  selfM.put("session", session);
  selfM.put("sc", sc);

  sM.put( driverCode, selfM );

  Runnable runnable = new Runnable() {
    @Override
    public void run() {
      WmLog.busLog( "开始推送" );
      try {
        long startTimeMillis = System.currentTimeMillis();
        while (!Thread.currentThread().isInterrupted()) {
          long curTimeMillis = System.currentTimeMillis();
          if ((curTimeMillis-startTimeMillis) >= (long) INTERVAL_TIME) {
            break;
          }

          String pushMsgData = WmJedisClient.get( wlc.driverPushMsg+driverCode );
          WmLog.busLog( "pushMsgData is "+pushMsgData+", driverCode is "+driverCode );
          if (StringUtils.isEmpty(pushMsgData)) {
            break;
          }

        	try {
            //连接断掉的情况不处理redis消息源，因为有其它server处理或者等它过期
            if (sM.get(driverCode) != null) {
              session.sendText( pushMsgData );
              //默认认为是发送成功，不需要额外判断
              WmJedisClient.del( wlc.driverPushMsg+driverCode );
            } else {
            	WmLog.busLog( "driverCode["+driverCode+"] session channel closed." );
            }
          } catch (Exception e) {
          	WmLog.busLog( "exception message is " + e.getMessage()+ ", driverCode["+driverCode+"] session channel may be closed." );
          }
  			}
  		} catch (Exception e) {
  			WmLog.sysLog( "WmLbsPushServer onOpen occur exception, message is "+ e.getMessage() +", stack trace is "+e.getStackTrace().toString() );
  		}
  	}
  };

  // 第二个参数为首次执行的延时时间，第三个参数为定时执行的间隔时间
  sc.scheduleAtFixedRate(runnable, 0, INTERVAL_TIME, TimeUnit.MILLISECONDS);
  WmLog.sysLog("推送连接成功 ==> [driverCode=" + driverCode + ", cityCode=" + cityCode + ", connTime=" + connTime + "]");
}

@OnClose
public void onClose(Session session) throws IOException {
  if (sM.get(selfM.get("driverCode")) != null) {
    ScheduledExecutorService sc = (ScheduledExecutorService) sM.get(selfM.get("driverCode")).get( "sc" );
    sc.shutdownNow();
    sM.remove(selfM.get("driverCode"));
  }

  WmLog.sysLog("推送连接断开 ==> [driverCode=" + selfM.get("driverCode") + ", cityCode=" + selfM.get("cityCode") + ", connTime=" + selfM.get("connTime") + "]");
}
```

5.（选做）本机使用G1 GC启动一个程序，仿照课上案例分析一下JVM情况。

设置最大堆内存和初始化堆内存都为1G，使用G1GC，关闭自适应大小策略（防止GC自动计算出Eden、From和To区的大小），最小GC等待时间为200毫秒，启动jar包：

>/Library/Java/JavaVirtualMachines/jdk-12.0.2.jdk/Contents/Home/bin/java -Xmx1g -Xms1g -XX:-UseAdaptiveSizePolicy -XX:+UseG1GC -XX:MaxGCPauseMillis=200 -jar /geektime/homework/week1/作业相关/gateway-server-0.0.1-SNAPSHOT.jar
>

执行结果：

>WARNING: An illegal reflective access operation has occurred

>WARNING: Illegal reflective access by org.springframework.cglib.core.ReflectUtils$1 (jar:file:/geektime/homework/week1/作业相关/gateway-server-0.0.1-SNAPSHOT.jar!/BOOT-INF/lib/spring-core-5.0.8.RELEASE.jar!/) to method java.lang.ClassLoader.defineClass(java.lang.String,byte[],int,int,java.security.ProtectionDomain)

>WARNING: Please consider reporting this to the maintainers of org.springframework.cglib.core.ReflectUtils$1

>WARNING: Use --illegal-access=warn to enable warnings of further illegal reflective access operations

>WARNING: All illegal access operations will be denied in a future release

查看jar包启动进程id

>jps -l

执行结果：

> 1313 /geektime/homework/week1/作业相关/gateway-server-0.0.1-SNAPSHOT.jar

查看堆占用情况：

>/Library/Java/JavaVirtualMachines/jdk-12.0.2.jdk/Contents/Home/bin/jhsdb jmap --heap --pid 1313

执行结果：

```java
Attaching to process ID 1313, please wait...
Debugger attached successfully.
Server compiler detected.
JVM version is 12.0.2+10

using thread-local object allocation.
Garbage-First (G1) GC with 8 thread(s)   使用了8线程的G1

Heap Configuration:
   MinHeapFreeRatio         = 40  空闲堆空间的最小百分比，空闲堆空间计算公式：HeapFreeRatio =(CurrentFreeHeapSize/CurrentTotalHeapSize) * 100，值域：[0,100]，HeapFreeRatio < MinHeapFreeRatio需要进行堆扩容，时机在每次垃圾回收之后。
   MaxHeapFreeRatio         = 70  空闲堆空间的最大百分比，HeapFreeRatio > MaxHeapFreeRatio时需要堆缩容，时机同上。
   MaxHeapSize              = 1073741824 (1024.0MB)
   NewSize                  = 1363144 (1.2999954223632812MB)  Young区默认大小
   MaxNewSize               = 643825664 (614.0MB)  最大的Young区的大小为614MB
   OldSize                  = 5452592 (5.1999969482421875MB)  年老代默认大小
   NewRatio                 = 2  Young区和年老代堆空间比值，年轻代：年老代 = 1:2
   SurvivorRatio            = 8  两个Survivor区和Eden区的堆空间比值为 8，表示 S0 ： S1 ：Eden = 1：1：8
   MetaspaceSize            = 21807104 (20.796875MB)  JVM 元空间的默认值
   CompressedClassSpaceSize = 1073741824 (1024.0MB)
   MaxMetaspaceSize         = 17592186044415 MB  JVM 元空间的最大值
   G1HeapRegionSize         = 1048576 (1.0MB)  G1将堆空间分隔为若干个region，每个占用1MB空间

Heap Usage:
G1 Heap:
   regions  = 1024  分了1024个region
   capacity = 1073741824 (1024.0MB)  G1堆总共所占内存容量为1024MB
   used     = 131464752 (125.37455749511719MB)
   free     = 942277072 (898.6254425048828MB)
   12.243609130382538% used  12%的空间使用率
G1 Young Generation:
Eden Space:
   regions  = 108  Eden区分了108个region
   capacity = 342884352 (327.0MB)
   used     = 113246208 (108.0MB)
   free     = 229638144 (219.0MB)
   33.027522935779814% used  Eden区已使用了33%的内存
Survivor Space:
   regions  = 17  幸存区分了17个region
   capacity = 17825792 (17.0MB)
   used     = 17825792 (17.0MB)
   free     = 0 (0.0MB)  幸存区未实际使用所占内存
   100.0% used
G1 Old Generation:
   regions  = 2  年老代分了2个region
   capacity = 713031680 (680.0MB)
   used     = 392752 (0.3745574951171875MB)
   free     = 712638928 (679.6254425048828MB)
   0.05508198457605699% used  年老代已使用了0.05%的内存
```
